dspygraph/__init__.py
dspygraph/node.py
dspygraph/workflow.py
dspygraph-0.1.0.dist-info/METADATA
dspygraph-0.1.0.dist-info/WHEEL
dspygraph-0.1.0.dist-info/licenses/LICENSE
dspygraph-0.1.0.dist-info/RECORD
