Metadata-Version: 2.4
Name: dspygraph
Version: 0.1.0
Summary: A lightweight framework for building graph-based workflows with DSPy nodes
Project-URL: Homepage, https://github.com/joelgrus/dspygraph
Project-URL: Repository, https://github.com/joelgrus/dspygraph
Project-URL: Issues, https://github.com/joelgrus/dspygraph/issues
Project-URL: Documentation, https://github.com/joelgrus/dspygraph#readme
Author-email: Joel Grus <joel@joelgrus.com>
Maintainer-email: Joel Grus <joel@joelgrus.com>
License: MIT License
License-File: LICENSE
Keywords: ai,dspy,graph,language-models,llm,machine-learning,workflow
Classifier: Development Status :: 3 - Alpha
Classifier: Intended Audience :: Developers
Classifier: Intended Audience :: Science/Research
Classifier: License :: OSI Approved :: MIT License
Classifier: Operating System :: OS Independent
Classifier: Programming Language :: Python :: 3
Classifier: Programming Language :: Python :: 3.11
Classifier: Programming Language :: Python :: 3.12
Classifier: Topic :: Scientific/Engineering :: Artificial Intelligence
Classifier: Topic :: Software Development :: Libraries :: Python Modules
Requires-Python: >=3.11
Requires-Dist: dspy>=2.6.27
Provides-Extra: dev
Requires-Dist: build>=1.2.0; extra == 'dev'
Requires-Dist: pytest>=8.4.1; extra == 'dev'
Requires-Dist: ruff>=0.1.0; extra == 'dev'
